aioyoutube/__init__.py
aioyoutube/client.py
aioyoutube/exceptions.py
aioyoutube/http.py
aioyoutube/parse.py
aioyoutube/valid.py
aioyoutube.py-0.7.0.dist-info/LICENSE
aioyoutube.py-0.7.0.dist-info/METADATA
aioyoutube.py-0.7.0.dist-info/WHEEL
aioyoutube.py-0.7.0.dist-info/top_level.txt
aioyoutube.py-0.7.0.dist-info/RECORD
