Metadata-Version: 2.1
Name: aioyoutube.py
Version: 0.7.0
Summary: An asynchronous Python wrapper for the YouTube Data API
Home-page: https://github.com/im-mde/aioyoutube.py
Author: im-mde
License: MIT
Platform: UNKNOWN
Classifier: Development Status :: 4 - Beta
Classifier: License :: OSI Approved :: MIT License
Classifier: Intended Audience :: Developers
Classifier: Natural Language :: English
Classifier: Operating System :: OS Independent
Classifier: Programming Language :: Python :: 3
Classifier: Topic :: Internet
Classifier: Topic :: Software Development :: Libraries
Classifier: Topic :: Software Development :: Libraries :: Python Modules
Classifier: Topic :: Utilities
Requires-Python: >=3.7
Requires-Dist: aiohttp (>=3.6.0)
